MANIFEST.in
setup.py
kiwipiepy_model/__init__.py
kiwipiepy_model/_version.py
kiwipiepy_model/combiningRule.txt
kiwipiepy_model/default.dict
kiwipiepy_model/extract.mdl
kiwipiepy_model/multi.dict
kiwipiepy_model/sj.knlm
kiwipiepy_model/sj.morph
kiwipiepy_model/skipbigram.mdl
kiwipiepy_model/typo.dict
kiwipiepy_model.egg-info/PKG-INFO
kiwipiepy_model.egg-info/SOURCES.txt
kiwipiepy_model.egg-info/dependency_links.txt
kiwipiepy_model.egg-info/not-zip-safe
kiwipiepy_model.egg-info/top_level.txt