Metadata-Version: 2.1
Name: kiwipiepy_model
Version: 0.21.0
Summary: Model for kiwipiepy
Home-page: https://github.com/bab2min/kiwipiepy
Author: bab2min
Author-email: bab2min@gmail.com
License: LGPL v3 License
Keywords: Korean morphological analysis
Classifier: Development Status :: 3 - Alpha
Classifier: Intended Audience :: Developers
Classifier: Intended Audience :: Science/Research
Classifier: Topic :: Software Development :: Libraries
Classifier: Topic :: Text Processing :: Linguistic
Classifier: License :: OSI Approved :: GNU Lesser General Public License v3 (LGPLv3)
Classifier: Programming Language :: Python :: 3
Classifier: Programming Language :: C++
